{"chunk_definitions":[{"row":9,"row_count":1,"visible":true,"expansion_state":0,"options":{"engine":"r","label":"setup","include":false},"document_id":"BCC82516","chunk_id":"csetup_chunk","chunk_label":"setup"},{"row":15,"row_count":1,"visible":true,"expansion_state":0,"options":{"engine":"r","label":"unnamed-chunk-4"},"document_id":"2CB0290E","chunk_id":"c442crdxn4s50","chunk_label":"unnamed-chunk-1"},{"row":58,"row_count":1,"visible":true,"expansion_state":0,"options":{"engine":"r","label":"unnamed-chunk-5"},"document_id":"2CB0290E","chunk_id":"ccejgizwy62gw","chunk_label":"unnamed-chunk-2"},{"row":70,"row_count":1,"visible":true,"expansion_state":0,"options":{"engine":"r","label":"unnamed-chunk-6"},"document_id":"2CB0290E","chunk_id":"c37ixv6wa7cna","chunk_label":"unnamed-chunk-3"},{"row":84,"row_count":1,"visible":true,"expansion_state":0,"options":{"engine":"r","label":"unnamed-chunk-7"},"document_id":"BCC82516","chunk_id":"c7zn1mb5zfz2k","chunk_label":"unnamed-chunk-4"}],"doc_write_time":1622064696,"working_dir":null,"default_chunk_options":{"echo":true}}